JCompile/__init__.py
JCompile/compiler.py
run.py
jcompyle-0.1.2.dist-info/entry_points.txt
jcompyle-0.1.2.dist-info/WHEEL
jcompyle-0.1.2.dist-info/METADATA
jcompyle-0.1.2.dist-info/RECORD
