Metadata-Version: 2.1
Name: jcompyle
Version: 0.1.2
Summary: simple json compiler
Author: amir
Author-email: amir.daaee@gmail.com
Requires-Python: >=3.8,<4.0
Classifier: Programming Language :: Python :: 3
Classifier: Programming Language :: Python :: 3.10
Classifier: Programming Language :: Python :: 3.8
Classifier: Programming Language :: Python :: 3.9
